env2dict/__init__.py
env2dict/env_parse.py
env2dict-0.1.0.dist-info/LICENSE
env2dict-0.1.0.dist-info/METADATA
env2dict-0.1.0.dist-info/WHEEL
env2dict-0.1.0.dist-info/top_level.txt
env2dict-0.1.0.dist-info/RECORD
